Workbook

Sheet Start Here
A1: Excel Practice Workbook – [SOLUTIONS]
A2: Operations Analyst track · Practice exercises built on the same skills the QC audit checks, using different data and scenarios.
A4: Note: All numbers, names and cell addresses in this workbook are deliberately different from the audit paper. Focus on the METHOD – the same thinking works whatever the cells or values are.
A9: How to use this workbook
B10: 1. Work through the sheets in order (Ex1 → Ex8). Each sheet has blue task boxes that tell you what to do.
B11: 2. Type your formulas or answers ONLY in the light-yellow cells. Do not type the result as a number when a formula is asked for.
B12: 3. For 'Why?' questions, write 1–3 sentences in the yellow answer box – the audit asks you to explain, not just compute.
B13: 4. Some tasks use Excel features (Sort, Filter, Freeze Panes, Text to Columns, Remove Duplicates, PivotTable). Do them on the sheet itself.
B14: 5. When finished, compare with the Solutions workbook given by your trainer.
A16: Colour legend
C17: Your input – type formula / answer here
C18: Task / instructions
C19: Model answer (Solutions workbook only)
A21: Exercise map
B22: Sheet | C22: Skills practised
B23: Ex1_Formulas | C23: SUM, COUNT, AVERAGE with blanks & zeros; percentage variance
B24: Ex2_References | C24: Relative vs absolute ($) references; fixing a broken copied formula
B25: Ex3_SortFilter | C25: Sort, multi-level sort, Filter, Freeze Panes, % formatting
B26: Ex4_Errors | C26: Reading #N/A and #VALUE! correctly before 'fixing' them
B27: Ex5_TextClean | C27: TRIM, CLEAN, PROPER, Text to Columns, standardising IDs
B28: Ex6_Duplicates | C28: Remove Duplicates on the right fields; before/after validation
B29: Ex7_PivotRaw / Ex7_Pivot | C29: Structuring data, PivotTable, Slicer, PivotChart
B30: Ex8_Scenarios | C30: 20 scenario MCQs in the audit style – choose the best action

Sheet Ex1_Formulas
A1: Ex1 – Core Formulas: SUM, COUNT, AVERAGE, % Variance
A2: Always reference cells – never type the numbers into the formula. Watch how blanks and zeros are treated.
A4: Audit skills: SUM vs typed numbers · COUNT includes zeros · AVERAGE ignores blanks · % variance = (Actual − Target) ÷ Target.
A9: A. Weekly dispatch count – total
A10: A colleague typed =265+340+195+415 to get the total. In E12 write a formula that will still be correct if any week's number changes later. Then change B13 to 455 and watch the total update (change it back afterwards).
A11: Week | B11: Dispatches
A12: Week 1 | B12: 265 | D12: Total (formula) → | E12: =SUM(B12:B15) -> 1215
A13: Week 2 | B13: 340 | D13: Why is this better than typing the numbers?
A14: Week 3 | B14: 195 | D14: SUM links the total to the cells, so it recalculates automatically if any value changes. Typed numbers are frozen and become wrong silently. Result = 1,215.
A15: Week 4 | B15: 415
A17: B. Tickets resolved per agent – how many cells contain numbers?
A18: Some agents resolved 0 tickets; some cells are blank (agent absent). A teammate says 0 should not be counted. In the yellow cell (column E) write a formula that counts the cells containing numbers and state the result.
A19: Agent | B19: Tickets resolved
A20: Agent A | B20: 42 | D20: Count of numeric cells → | E20: =COUNT(B20:B27) -> 6
A21: Agent B | D21: Should the zeros be counted? Why?
A22: Agent C | B22: 0 | D22: Yes. 0 is a number, so COUNT includes it; only the 2 blank cells are ignored. Result = 6 (42, 0, 67, 85, 0, 33).
A23: Agent D | B23: 67
A24: Agent E | D24: Bonus: count the blank cells → | E24: =COUNTBLANK(B20:B27) -> 2
A25: Agent F | B25: 85
A26: Agent G | B26: 0
A27: Agent H | B27: 33
A29: C. Quality scores – average
A30: Two audits were not done yet (blank). A teammate calculates the average as total ÷ 6 because there are 6 cells. Write the correct formula in the first yellow cell, and in the second yellow cell show the WRONG result the teammate would get (use a formula).
A31: Audit | B31: Score
A32: Audit 1 | B32: 72 | D32: Correct average → | E32: =AVERAGE(B32:B37) -> 79
A33: Audit 2 | D33: Teammate's wrong average → | E33: =SUM(B32:B37)/6 -> 52.666667
A34: Audit 3 | B34: 86 | D34: Explain the difference
A35: Audit 4 | B35: 64 | D35: AVERAGE ignores genuinely blank cells: 316 ÷ 4 = 79. Dividing by 6 treats the two blanks as zeros and understates the average (52.67).
A36: Audit 5
A37: Audit 6 | B37: 94
A39: D. Target vs Actual – percentage variance
A40: For each team, calculate % variance = (Actual − Target) ÷ Target in column D, format it as a percentage, and in column E write 'Above' or 'Below' target. One associate reported Team 1 as '39% variance' because 520 − 481 = 39. Explain why that is wrong.
A41: Team | B41: Target | C41: Actual | D41: % Variance | E41: Above / Below
A42: Team 1 | B42: 520 | C42: 481 | D42: =(C42-B42)/B42 -> -0.075 | E42: =IF(C42>B42,"Above",IF(C42<B42,"Below","On target")) -> Below
A43: Team 2 | B43: 260 | C43: 325 | D43: =(C43-B43)/B43 -> 0.25 | E43: =IF(C43>B43,"Above",IF(C43<B43,"Below","On target")) -> Above
A44: Team 3 | B44: 1400 | C44: 1526 | D44: =(C44-B44)/B44 -> 0.09 | E44: =IF(C44>B44,"Above",IF(C44<B44,"Below","On target")) -> Above
A45: Team 4 | B45: 84 | C45: 63 | D45: =(C45-B45)/B45 -> -0.25 | E45: =IF(C45>B45,"Above",IF(C45<B45,"Below","On target")) -> Below
A46: Team 5 | B46: 650 | C46: 650 | D46: =(C46-B46)/B46 -> 0 | E46: =IF(C46>B46,"Above",IF(C46<B46,"Below","On target")) -> On target
A47: Why is '39% variance' wrong?
A48: 39 is the difference in units, not a percentage. It must be divided by the target: −39 ÷ 520 = −7.5%, i.e. 7.5% below target.

Sheet Ex2_References
A1: Ex2 – Relative vs Absolute References
A2: Relative references (F14) move when copied. Absolute references ($K$6) stay fixed. Mixed use is normal: each row's own amount, one fixed rate.
A4: Audit skills: absolute reference to a fixed rate · relative references adjust when copied · smallest fix to a broken copied formula.
J6: Commission rate | K6: 0.045
J7: Sales tax rate | K7: 0.0725
A9: Task 1: Column D already contains a formula someone wrote in D13 as =C13*K6 and copied down. Look at the results – only the first row is right. In column E write a corrected formula in E13 and copy it down to E32.
A10: Task 2: In F13 calculate Sales tax on the sales amount using the Sales tax rate in K7, copy down. Task 3: Answer the questions below the table.
A12: Rep | B12: Region | C12: Sales Amount | D12: Commission (faulty – given) | E12: Commission (your fix) | F12: Sales tax (your formula)
A13: REP-101 | B13: North | C13: 58750 | D13: =C13*K6 -> 2643.75 | E13: =C13*$K$6 -> 2643.75 | F13: =C13*$K$7 -> 4259.375
A14: REP-102 | B14: North | C14: 46500 | D14: =C14*K7 -> 3371.25 | E14: =C14*$K$6 -> 2092.5 | F14: =C14*$K$7 -> 3371.25
A15: REP-103 | B15: West | C15: 91250 | D15: =C15*K8 -> 0 | E15: =C15*$K$6 -> 4106.25 | F15: =C15*$K$7 -> 6615.625
A16: REP-104 | B16: West | C16: 93000 | D16: =C16*K9 -> 0 | E16: =C16*$K$6 -> 4185 | F16: =C16*$K$7 -> 6742.5
A17: REP-105 | B17: West | C17: 48500 | D17: =C17*K10 -> 0 | E17: =C17*$K$6 -> 2182.5 | F17: =C17*$K$7 -> 3516.25
A18: REP-106 | B18: North | C18: 28250 | D18: =C18*K11 -> 0 | E18: =C18*$K$6 -> 1271.25 | F18: =C18*$K$7 -> 2048.125
A19: REP-107 | B19: North | C19: 54750 | D19: =C19*K12 -> 0 | E19: =C19*$K$6 -> 2463.75 | F19: =C19*$K$7 -> 3969.375
A20: REP-108 | B20: North | C20: 75500 | D20: =C20*K13 -> 0 | E20: =C20*$K$6 -> 3397.5 | F20: =C20*$K$7 -> 5473.75
A21: REP-109 | B21: North | C21: 80750 | D21: =C21*K14 -> 0 | E21: =C21*$K$6 -> 3633.75 | F21: =C21*$K$7 -> 5854.375
A22: REP-110 | B22: East | C22: 44750 | D22: =C22*K15 -> 0 | E22: =C22*$K$6 -> 2013.75 | F22: =C22*$K$7 -> 3244.375
A23: REP-111 | B23: West | C23: 50000 | D23: =C23*K16 -> 0 | E23: =C23*$K$6 -> 2250 | F23: =C23*$K$7 -> 3625
A24: REP-112 | B24: East | C24: 63500 | D24: =C24*K17 -> 0 | E24: =C24*$K$6 -> 2857.5 | F24: =C24*$K$7 -> 4603.75
... A32: REP-120 | B32: West | C32: 72000 | D32: =C32*K25 -> 0 | E32: =C32*$K$6 -> 3240 | F32: =C32*$K$7 -> 5220
B33: Total | C33: =SUM(C13:C32) -> 1218000 | E33: =SUM(E13:E32) -> 54810
A35: Q1. Click D15. What did K6 become, and why are the faulty results wrong?
A36: D15 refers to K8 (blank) because the relative reference moved down with the copy. D14 even picked up the Sales tax rate in K7. Only D13 uses the real commission rate in K6.
A37: Q2. What is the smallest change to fix the faulty formula? Which part stays relative?
A38: Change K6 to $K$6: =C13*$K$6. C13 stays relative because each row must use its own sales amount; the rate is locked.
A39: Q3. A colleague says Excel 'broke' the formula when C13 became C14 on the next row. Is Excel wrong?
A40: No. C13 is a relative reference, so it correctly adjusts to C14 for the next row – that is exactly what we want for the row's own amount.
A41: Q4. What would $K6 and K$6 do differently from $K$6?
A42: $K6 locks only the column (row can change); K$6 locks only the row (column can change). $K$6 locks both. Copying down a column, K$6 would also work, but $K$6 is safest.

Sheet Ex3_SortFilter
A1: Ex3 – Sort, Filter, Freeze Panes & Formatting | I1: TASKS (do them on the data in A:G)
I2: T1. Your lead wants to review the 5 biggest transactions first but must still see ALL 420 rows. Which feature? Do it, then record the top 5 Txn IDs and amounts below.
A3: Audit skills: Sort keeps every row visible · Filter hides temporarily without deleting · Freeze Panes changes only the view · % formatting changes display, not value. The heading row of this dataset is row 9 – data runs from row 10 to row 429. | I3: Sort – Amount, Largest to Smallest. Filter would hide rows; Sort only reorders.
I4: T2. The Phoenix manager wants to see only Phoenix records for a call, and everything else must be back afterwards untouched. Do it, write how many rows were shown, then clear it.
I5: Filter on Branch → Phoenix. Records are only hidden, not deleted; Clear Filter restores them.
I6: T3. When you scroll to row 365 you cannot see the headings (row 9). Fix this without moving or copying any data. Careful: the headings are NOT in row 1.
I7: Select A10 → View → Freeze Panes → Freeze Panes (rows 1–9 stay visible). Freeze Top Row would only keep row 1, which is wrong here. Data is unchanged.
I8: T4. Discount Rate shows decimals (e.g. 0.085) but the report needs percentages (8.5%). Make the column display as % WITHOUT changing the stored value.
A9: Txn ID | B9: Date | C9: Branch | D9: Category | E9: Amount ($) | F9: Discount Rate | G9: Status | I9: Home → Number → Percentage (1 decimal). Value stays 0.085; do NOT retype it as 8.5.
A10: TXN-50001 | B10: 46203 | C10: Seattle | D10: Stationery | E10: 11595 | F10: 0.085 | G10: Delivered | I10: T5. Sort by Branch (A→Z) and within each branch by Amount (largest first). Which branch appears first, and what is its top amount?
A11: TXN-50002 | B11: 46145 | C11: Denver | D11: Appliances | E11: 46931 | F11: 0.065 | G11: Delivered | I11: Data → Sort → add level: Branch A-Z, then Amount Largest-Smallest. Austin comes first.
A12: TXN-50003 | B12: 46220 | C12: Seattle | D12: Furniture | E12: 68372 | F12: 0.02 | G12: Delivered
A13: TXN-50004 | B13: 46251 | C13: Seattle | D13: Appliances | E13: 64788 | F13: 0.045 | G13: In Transit | I13: Record your answers
A14: TXN-50005 | B14: 46171 | C14: Austin | D14: Stationery | E14: 58362 | F14: 0.085 | G14: Delivered | I14: T1 – Rank | J14: Txn ID | K14: Amount
A15: TXN-50006 | B15: 46180 | C15: Phoenix | D15: Furniture | E15: 14549 | F15: 0.11 | G15: Delivered | I15: Top 1 | J15: =INDEX($A$10:$A$429,MATCH(K15,$E$10:$E$429,0)) -> TXN-50105 | K15: =LARGE($E$10:$E$429,1) -> 97814
A16: TXN-50007 | B16: 46158 | C16: Seattle | D16: Stationery | E16: 49990 | F16: 0.045 | G16: In Transit | I16: Top 2 | J16: =INDEX($A$10:$A$429,MATCH(K16,$E$10:$E$429,0)) -> TXN-50226 | K16: =LARGE($E$10:$E$429,2) -> 97415
A17: TXN-50008 | B17: 46194 | C17: Austin | D17: Electronics | E17: 59272 | F17: 0.11 | G17: Cancelled | I17: Top 3 | J17: =INDEX($A$10:$A$429,MATCH(K17,$E$10:$E$429,0)) -> TXN-50336 | K17: =LARGE($E$10:$E$429,3) -> 97233
A18: TXN-50009 | B18: 46233 | C18: Austin | D18: Furniture | E18: 93236 | F18: 0.11 | G18: Delivered | I18: Top 4 | J18: =INDEX($A$10:$A$429,MATCH(K18,$E$10:$E$429,0)) -> TXN-50124 | K18: =LARGE($E$10:$E$429,4) -> 97114
A19: TXN-50010 | B19: 46151 | C19: Phoenix | D19: Appliances | E19: 87230 | F19: 0.11 | G19: Cancelled | I19: Top 5 | J19: =INDEX($A$10:$A$429,MATCH(K19,$E$10:$E$429,0)) -> TXN-50183 | K19: =LARGE($E$10:$E$429,5) -> 96820
A20: TXN-50011 | B20: 46172 | C20: Seattle | D20: Stationery | E20: 70031 | F20: 0.045 | G20: Returned | I20: T2 – Phoenix rows shown | J20: =COUNTIF($C$10:$C$429,"Phoenix") -> 105
A21: TXN-50012 | B21: 46208 | C21: Denver | D21: Appliances | E21: 57515 | F21: 0.085 | G21: Returned | I21: T2 – Rows visible after clearing filter | J21: =COUNTA($A$10:$A$429) -> 420
A22: TXN-50013 | B22: 46261 | C22: Denver | D22: Furniture | E22: 46861 | F22: 0.11 | G22: Delivered | I22: T5 – First branch after sort | J22: Austin
A23: TXN-50014 | B23: 46237 | C23: Phoenix | D23: Stationery | E23: 61365 | F23: 0.14 | G23: Cancelled | I23: T5 – Its top amount | J23: =_xlfn.MAXIFS($E$10:$E$429,$C$10:$C$429,"Austin") -> 97814
A24: TXN-50015 | B24: 46246 | C24: Seattle | D24: Electronics | E24: 30859 | F24: 0.11 | G24: Delivered | I24: T4 – Stored value of F10 after formatting | J24: =F10 -> 0.085
A25: TXN-50016 | B25: 46189 | C25: Denver | D25: Stationery | E25: 49360 | F25: 0.02 | G25: In Transit
A26: TXN-50017 | B26: 46138 | C26: Phoenix | D26: Electronics | E26: 65880 | F26: 0.085 | G26: Delivered | I26: Note: the formulas above are only checks – in the audit you do the Sort/Filter with the Excel feature itself.
A27: TXN-50018 | B27: 46262 | C27: Denver | D27: Electronics | E27: 56157 | F27: 0.065 | G27: Delivered
A28: TXN-50019 | B28: 46245 | C28: Phoenix | D28: Furniture | E28: 60028 | F28: 0.085 | G28: Delivered
A29: TXN-50020 | B29: 46149 | C29: Seattle | D29: Stationery | E29: 60602 | F29: 0.085 | G29: Delivered
A30: TXN-50021 | B30: 46123 | C30: Seattle | D30: Furniture | E30: 93537 | F30: 0.02 | G30: Returned
A31: TXN-50022 | B31: 46188 | C31: Seattle | D31: Stationery | E31: 4105 | F31: 0.02 | G31: Cancelled
A32: TXN-50023 | B32: 46161 | C32: Phoenix | D32: Electronics | E32: 67203 | F32: 0.14 | G32: In Transit
A33: TXN-50024 | B33: 46235 | C33: Phoenix | D33: Stationery | E33: 26946 | F33: 0.14 | G33: In Transit
A34: TXN-50025 | B34: 46250 | C34: Austin | D34: Electronics | E34: 89029 | F34: 0.02 | G34: Delivered
A35: TXN-50026 | B35: 46150 | C35: Austin | D35: Electronics | E35: 15991 | F35: 0.085 | G35: In Transit
A36: TXN-50027 | B36: 46113 | C36: Phoenix | D36: Electronics | E36: 95028 | F36: 0.045 | G36: Delivered
A37: TXN-50028 | B37: 46249 | C37: Austin | D37: Furniture | E37: 6800 | F37: 0.02 | G37: Delivered
A38: TXN-50029 | B38: 46196 | C38: Denver | D38: Electronics | E38: 82015 | F38: 0.065 | G38: Delivered
... A429: TXN-50420 | B429: 46205 | C429: Austin | D429: Appliances | E429: 61134 | F429: 0.045 | G429: In Transit

Sheet Ex4_Errors
A1: Ex4 – Reading Errors Correctly (#N/A and #VALUE!)
A2: An error is a message. Read what it is telling you before you hide it or rewrite the formula.
A4: Audit skills: #N/A = no match found (investigate before hiding) · #VALUE! = a value of the wrong type (text in a calculation) – check the data, not the operator.
A9: A. Lookup – Employee master vs requests
A10: In F13 write a lookup that returns the employee name for the ID in E13 from the master list (A:C). Copy down. most of the 18 IDs work, but 3 return #N/A. Do NOT wrap in IFERROR yet – in column H write WHY each #N/A happened.
A12: Emp ID | B12: Name | C12: Dept | E12: Request ID | F12: Name (lookup) | G12: Result / Status | H12: Reason (if #N/A)
A13: E1021 | B13: Emily Carter | C13: Ops | E13: E1024 | F13: =VLOOKUP(E13,$A$13:$B$32,2,FALSE()) -> Michael Reed | G13: Found
A14: E1022 | B14: James Walker | C14: Finance | E14: E1030 | F14: =VLOOKUP(E14,$A$13:$B$32,2,FALSE()) -> Tyler Morgan | G14: Found
A15: E1023 | B15: Olivia Brooks | C15: HR | E15: E1021 | F15: =VLOOKUP(E15,$A$13:$B$32,2,FALSE()) -> Emily Carter | G15: Found
A16: E1024 | B16: Michael Reed | C16: Ops | E16: E1047 | F16: #N/A (expected) | G16: Not found | H16: E1047 is not in the master list at all – genuinely missing (check with source team).
A17: E1025 | B17: Sophia Turner | C17: Audit | E17: E1033 | F17: =VLOOKUP(E17,$A$13:$B$32,2,FALSE()) -> Lauren Hayes | G17: Found
A18: E1026 | B18: Daniel Hughes | C18: Finance | E18: E1038 | F18: =VLOOKUP(E18,$A$13:$B$32,2,FALSE()) -> Nathan Bryant | G18: Found
A19: E1027 | B19: Ava Mitchell | C19: Ops | E19: E1026 | F19: =VLOOKUP(E19,$A$13:$B$32,2,FALSE()) -> Daniel Hughes | G19: Found
A20: E1028 | B20: Ryan Cooper | C20: HR | E20: E1032 | F20: #N/A (expected) | G20: Not found | H20: Trailing space – 'E1032 ' ≠ 'E1032'. Fix with TRIM, not by hiding the error.
A21: E1029 | B21: Grace Bennett | C21: Audit | E21: E1029 | F21: =VLOOKUP(E21,$A$13:$B$32,2,FALSE()) -> Grace Bennett | G21: Found
A22: E1030 | B22: Tyler Morgan | C22: Ops | E22: E1040 | F22: =VLOOKUP(E22,$A$13:$B$32,2,FALSE()) -> Eric Russell | G22: Found
A23: E1031 | B23: Hannah Price | C23: Ops | E23: E1023 | F23: =VLOOKUP(E23,$A$13:$B$32,2,FALSE()) -> Olivia Brooks | G23: Found
A24: E1032 | B24: Kevin Foster | C24: Finance | E24: E1-035 | F24: #N/A (expected) | G24: Not found | H24: Entered in a different format (E1-035 vs E1035). Standardise the ID.
A25: E1033 | B25: Lauren Hayes | C25: HR | E25: E1027 | F25: =VLOOKUP(E25,$A$13:$B$32,2,FALSE()) -> Ava Mitchell | G25: Found
A26: E1034 | B26: Brandon Ellis | C26: Ops | E26: E1039 | F26: =VLOOKUP(E26,$A$13:$B$32,2,FALSE()) -> Natalie Sanders | G26: Found
A27: E1035 | B27: Megan Ward | C27: Audit | E27: E1022 | F27: =VLOOKUP(E27,$A$13:$B$32,2,FALSE()) -> James Walker | G27: Found
A28: E1036 | B28: Justin Perry | C28: Finance | E28: E1031 | F28: =VLOOKUP(E28,$A$13:$B$32,2,FALSE()) -> Hannah Price | G28: Found
A29: E1037 | B29: Rachel Coleman | C29: Ops | E29: E1036 | F29: =VLOOKUP(E29,$A$13:$B$32,2,FALSE()) -> Justin Perry | G29: Found
A30: E1038 | B30: Nathan Bryant | C30: HR | E30: E1028 | F30: =VLOOKUP(E30,$A$13:$B$32,2,FALSE()) -> Ryan Cooper | G30: Found
A31: E1039 | B31: Natalie Sanders | C31: Audit
A32: E1040 | B32: Eric Russell | C32: Ops
A34: Q. Your teammate wants to wrap the formula in IFERROR(…,0) immediately because 'it works for the others'. What is the risk?
A35: #N/A means 'no match found'. Replacing it with 0 hides that a record is missing or mis-keyed, and 0 looks like a real value. First investigate each #N/A (missing, extra space, different format); only then decide how to handle it.
A37: B. #VALUE! – Order value
A38: In column E write =Qty × Unit Price for each order and copy down. Some rows return #VALUE!. In F, explain what Excel is telling you. Do NOT change the * operator – find the real cause.
A40: Order | B40: Qty | C40: Unit Price | E40: Order Value | F40: What is wrong?
A41: ORD-1 | B41: 12 | C41: 450 | E41: =B41*C41 -> 5400 | F41: OK
A42: ORD-2 | B42: 9 | C42: TBD | E42: #VALUE! (expected) | F42: 'TBD' is text, not a number – multiplication cannot use text. Get the real value from source; the formula is fine.
A43: ORD-3 | B43: 22 | C43: 135 | E43: =B43*C43 -> 2970 | F43: OK
A44: ORD-4 | B44: Pending | C44: 340 | E44: #VALUE! (expected) | F44: 'Pending' is text, not a number – multiplication cannot use text. Get the real value from source; the formula is fine.
A45: ORD-5 | B45: 5 | C45: 999 | E45: =B45*C45 -> 4995 | F45: OK
A46: ORD-6 | B46: 14 | C46: N/A | E46: #VALUE! (expected) | F46: 'N/A' is text, not a number – multiplication cannot use text. Get the real value from source; the formula is fine.
A47: ORD-7 | B47: 7 | C47: 650 | E47: =B47*C47 -> 4550 | F47: OK
A49: Q. A teammate changes =B*C to =PRODUCT(B,C) and the error disappears (shows only Qty). Is the problem solved?
A50: No. PRODUCT simply ignores the text, so it returns a wrong value (e.g. 9 instead of 9 × price) with no warning. The data issue (missing price/qty) is still there and is now hidden – worse than the error.

Sheet Ex5_TextClean
A1: Ex5 – Text Cleaning: TRIM, CLEAN, PROPER, Text to Columns, ID format
A2: Each function fixes a different problem. Use LEN() to prove the cleaning worked.
A4: Audit skills: TRIM (spaces) · CLEAN (hidden characters) · PROPER (capitalisation) · Text to Columns with a delimiter · standardise ID formats before comparing.
A9: A. Customer names imported from a portal
A10: Fill columns C–G for each row. C: remove extra spaces. D: remove hidden non-printing characters (tabs / line breaks). E: fix capitalisation. F: do all three in one formula. G: LEN of your final name. Compare G with B (LEN of raw).
A11: Raw Name | B11: LEN (raw) | C11: TRIM only | D11: CLEAN only | E11: PROPER only | F11: Fully cleaned | G11: LEN (clean)
A12: aMANDA wilson | B12: =LEN(A12) -> 18 | C12: =TRIM(A12) -> aMANDA wilson | D12: =CLEAN(A12) -> aMANDA wilson | E12: =PROPER(A12) -> Amanda Wilson | F12: =PROPER(TRIM(CLEAN(A12))) -> Amanda Wilson | G12: =LEN(F12) -> 13
A13: ROBERT JOHNSON | B13: =LEN(A13) -> 16 | C13: =TRIM(A13) -> ROBERT JOHNSON | D13: =CLEAN(A13) -> ROBERT JOHNSON | E13: =PROPER(A13) -> Robert Johnson | F13: =PROPER(TRIM(CLEAN(A13))) -> Robert Johnson | G13: =LEN(F13) -> 14
A14: katie anderson | B14: =LEN(A14) -> 16 | C14: =TRIM(A14) -> katie anderson | D14: =CLEAN(A14) -> katie anderson | E14: =PROPER(A14) -> Katie Anderson | F14: =PROPER(TRIM(CLEAN(A14))) -> Katie Anderson | G14: =LEN(F14) -> 14
A15: cHRIS lee | B15: =LEN(A15) -> 13 | C15: =TRIM(A15) -> cHRIS lee | D15: =CLEAN(A15) -> cHRIS lee | E15: =PROPER(A15) -> Chris Lee | F15: =PROPER(TRIM(CLEAN(A15))) -> Chris Lee | G15: =LEN(F15) -> 9
A16: Nicole Martin | B16: =LEN(A16) -> 16 | C16: =TRIM(A16) -> Nicole Martin | D16: =CLEAN(A16) -> Nicole Martin | E16: =PROPER(A16) -> Nicole Martin | F16: =PROPER(TRIM(CLEAN(A16))) -> Nicole Martin | G16: =LEN(F16) -> 13
A17: matthew THOMPSON | B17: =LEN(A17) -> 19 | C17: =TRIM(A17) -> matthew THOMPSON | D17: =CLEAN(A17) -> matthew THOMPSON | E17: =PROPER(A17) -> Matthew Thompson | F17: =PROPER(TRIM(CLEAN(A17))) -> Matthew Thompson | G17: =LEN(F17) -> 16
A18: bRITTANY clark | B18: =LEN(A18) -> 17 | C18: =TRIM(A18) -> bRITTANY clark | D18: =CLEAN(A18) -> bRITTANY clark | E18: =PROPER(A18) -> Brittany Clark | F18: =PROPER(TRIM(CLEAN(A18))) -> Brittany Clark | G18: =LEN(F18) -> 14
A19: JOSHUA davis | B19: =LEN(A19) -> 16 | C19: =TRIM(A19) -> JOSHUA davis | D19: =CLEAN(A19) -> JOSHUA davis | E19: =PROPER(A19) -> Joshua Davis | F19: =PROPER(TRIM(CLEAN(A19))) -> Joshua Davis | G19: =LEN(F19) -> 12
A20: Q. Row 'Nicole Martin<tab>': compare LEN after TRIM only. Why does TRIM alone not fully fix it? Which function does?
A21: TRIM removes extra spaces only; the tab is a non-printing character, so CLEAN is needed to remove it. Use TRIM(CLEAN()) to handle both, PROPER for capitalisation, and confirm with LEN.
A23: B. Shipment codes – split into separate columns
A24: Each code has the pattern OrderID/City/Status. The '/' is only a separator. Select the codes in column A and use Data → Text to Columns → Delimited → Other: '/' with Destination = the first yellow cell in column C. Expected: 3 clean columns (Order ID, City, Status).
A25: Shipment Code | C25: Order ID | D25: City | E25: Status
A26: SHP-7781/Denver/Dispatched | C26: SHP-7781 | D26: Denver | E26: Dispatched
A27: SHP-7782/Austin/Packed | C27: SHP-7782 | D27: Austin | E27: Packed
A28: SHP-7783/Seattle/Delivered | C28: SHP-7783 | D28: Seattle | E28: Delivered
A29: SHP-7784/Phoenix/On Hold | C29: SHP-7784 | D29: Phoenix | E29: On Hold
A30: SHP-7785/Austin/Delivered | C30: SHP-7785 | D30: Austin | E30: Delivered
A31: SHP-7786/Denver/Packed | C31: SHP-7786 | D31: Denver | E31: Packed
A32: SHP-7787/Phoenix/Dispatched | C32: SHP-7787 | D32: Phoenix | E32: Dispatched
A33: Q. A colleague plans three LEFT/MID/RIGHT formulas per row. Why is Text to Columns simpler here?
A34: The separator is consistent ('/') in every row, so Text to Columns splits all rows in one step with no formulas to maintain, even though the parts have different lengths.
A36: C. Matching IDs from two systems
A37: System A stores IDs as 5-character text with leading zeros (00412). System B stores the same IDs as numbers (412). The business confirms they are the same IDs. In C convert System B to the System A format, then in D check whether they match.
A38: System A ID (text) | B38: System B ID | C38: B in A-format | D38: Match?
A39: 00412 | B39: 412 | C39: =TEXT(B39,"00000") -> 00412 | D39: =IF(A39=C39,"Match","Check") -> Match
A40: 00064 | B40: 64 | C40: =TEXT(B40,"00000") -> 00064 | D40: =IF(A40=C40,"Match","Check") -> Match
A41: 01375 | B41: 1375 | C41: =TEXT(B41,"00000") -> 01375 | D41: =IF(A41=C41,"Match","Check") -> Match
A42: 00009 | B42: 9 | C42: =TEXT(B42,"00000") -> 00009 | D42: =IF(A42=C42,"Match","Check") -> Match
A43: 00733 | B43: 737 | C43: =TEXT(B43,"00000") -> 00737 | D43: =IF(A43=C43,"Match","Check") -> Check
A44: 02041 | B44: 2041 | C44: =TEXT(B44,"00000") -> 02041 | D44: =IF(A44=C44,"Match","Check") -> Match
A45: 00560 | B45: 560 | C45: =TEXT(B45,"00000") -> 00560 | D45: =IF(A45=C45,"Match","Check") -> Match
A46: Q. After standardising, which ID still does not match, and what does that tell you?
A47: 00733 vs 737. After the format is aligned, the remaining difference is a real data difference (likely a keying error) – raise it, don't 'fix' it silently.

Sheet Ex6_Duplicates
A1: Ex6 – Removing Duplicates Safely & Validating the Result
A2: Remove true duplicate rows – not every repeated value. Then prove the change is explainable.
A4: Audit skills: Remove Duplicates on the fields that identify a record · same amount ≠ duplicate · validate row count and totals before and after cleaning.
A9: Invoice No | B9: Vendor | C9: Item | D9: Amount ($) | E9: Invoice Date | G9: Step 1 – BEFORE cleaning: record row count and total amount below. Type them as VALUES (or paste-special values) so they don't change later.
A10: INV-3151 | B10: Delta Logistics | C10: Office Chair | D10: 39769 | E10: 46249 | G10: Step 2 – Data → Remove Duplicates on A9:E71 using ALL columns (a true duplicate matches on every field).
A11: INV-3138 | B11: Delta Logistics | C11: Monitor | D11: 48305 | E11: 46206 | G11: Step 3 – AFTER cleaning: record the new row count and total; complete the validation table.
A12: INV-3144 | B12: Delta Logistics | C12: Cables | D12: 46787 | E12: 46223 | G12: Step 4 – Answer the questions.
A13: INV-3150 | B13: Crystal Office | C13: Laptop Stand | D13: 1764 | E13: 46216
A14: INV-3145 | B14: Crystal Office | C14: Monitor | D14: 25601 | E14: 46242 | G14: Validation check | H14: Before | I14: After
A15: INV-3127 | B15: Crystal Office | C15: Laptop Stand | D15: 49823 | E15: 46214 | G15: Row count (data rows) | H15: 62 | I15: 56
A16: INV-3105 | B16: Apex Supplies | C16: Courier Charges | D16: 32652 | E16: 46232 | G16: Total Amount ($) | H16: 1784624 | I16: 1596698
A17: INV-3139 | B17: Evergreen IT | C17: A4 Paper | D17: 54520 | E17: 46218 | G17: Rows removed (formula) | H17: =H15-I15 -> 6
A18: INV-3123 | B18: Delta Logistics | C18: Printer Toner | D18: 16768 | E18: 46221 | G18: Duplicates expected to be removed | H18: 6 | I18: ← given by data owner
A19: INV-3134 | B19: Evergreen IT | C19: Office Chair | D19: 32399 | E19: 46238 | G19: Check: removed = expected? | H19: =IF(H17=H18,"OK","Investigate") -> OK
A20: INV-3109 | B20: Crystal Office | C20: A4 Paper | D20: 21542 | E20: 46247 | G20: Amount removed (formula) | H20: =H16-I16 -> 187926
A21: INV-3142 | B21: Delta Logistics | C21: Printer Toner | D21: 21311 | E21: 46211
A22: INV-3129 | B22: Liberty Traders | C22: A4 Paper | D22: 22301 | E22: 46229 | G22: Q1. A teammate wants to Remove Duplicates using only the Amount column. How many rows would remain and why is that risky?
A23: INV-3137 | B23: Evergreen IT | C23: Printer Toner | D23: 4492 | E23: 46264 | G23: Only 52 rows would remain – 4 extra genuine invoices (different invoice no./item, same amount) would be deleted. Same amount ≠ duplicate record; use the fields that identify the record.
A24: INV-3103 | B24: Delta Logistics | C24: A4 Paper | D24: 3271 | E24: 46244 | G24: Q2. The file has fewer rows after cleaning. Is that enough to say the cleaning was correct?
A25: INV-3202 | B25: Liberty Traders | C25: Monitor | D25: 3084 | E25: 46231 | G25: No. Compare before/after row counts and totals and confirm the reduction (6 rows) matches what was expected. A lower count is only correct if it is explained by the cleaning done.
A26: INV-3112 | B26: Liberty Traders | C26: Office Chair | D26: 58073 | E26: 46219 | G26: Q3. After TRIM and ID standardisation the totals did not change but the row count did. Is that a problem?
A27: INV-3141 | B27: Delta Logistics | C27: Printer Toner | D27: 16922 | E27: 46264 | G27: Not necessarily – those steps change text, not amounts. But every change in row count must be traced to a specific step (e.g. duplicate removal) before reporting.
A28: INV-3147 | B28: Delta Logistics | C28: A4 Paper | D28: 1533 | E28: 46233
A29: INV-3124 | B29: Liberty Traders | C29: A4 Paper | D29: 20013 | E29: 46206
A30: INV-3121 | B30: Crystal Office | C30: Office Chair | D30: 42002 | E30: 46214
A31: INV-3103 | B31: Delta Logistics | C31: A4 Paper | D31: 3271 | E31: 46244
A32: INV-3140 | B32: Apex Supplies | C32: Monitor | D32: 48547 | E32: 46225
A33: INV-3110 | B33: Evergreen IT | C33: Courier Charges | D33: 6087 | E33: 46253
A34: INV-3111 | B34: Delta Logistics | C34: Cables | D34: 3084 | E34: 46211
A35: INV-3102 | B35: Apex Supplies | C35: Courier Charges | D35: 40198 | E35: 46249
A36: INV-3135 | B36: Evergreen IT | C36: Courier Charges | D36: 24556 | E36: 46237
A37: INV-3116 | B37: Delta Logistics | C37: Courier Charges | D37: 29616 | E37: 46205
A38: INV-3203 | B38: Evergreen IT | C38: Cables | D38: 42002 | E38: 46219
A39: INV-3104 | B39: Liberty Traders | C39: Monitor | D39: 30639 | E39: 46217
... A71: INV-3118 | B71: Apex Supplies | C71: Cables | D71: 30936 | E71: 46214

Sheet Ex7_PivotRaw
A1: Ex7 – Raw sales data (needs restructuring) | F1: TASK 1 – Before building any PivotTable, inspect this sheet. It has blank rows and a repeated heading row in the middle. Delete them so there is ONE heading row and one continuous block of data.
A3: Data heading is in row 9. | F3: Expected after cleaning: 1 heading row + 144 data rows (rows 10–153). Quick check: =COUNTA(A10:A500) should give 144.
F5: TASK 2 – Insert → PivotTable (new sheet). Rows: Region; Values: Sum of Amount. You should get one total per region, not 144 detail rows.
F7: TASK 3 – Add a Slicer for Category so a manager can click between categories without rebuilding the report.
A9: Month | B9: Region | C9: Category | D9: Amount ($) | F9: TASK 4 – Build a second PivotTable with Month in Rows and Sum of Amount, then add a PivotChart (Line) to show whether sales are rising or falling.
A10: Jan | B10: North | C10: Training | D10: 11782
A11: Jan | B11: West | C11: Training | D11: 13754 | F11: TASK 5 – If your PivotTable shows every single row, you have put Amount (or an ID) in Rows. Move Amount to Values and set it to Sum.
A12: Jan | B12: North | C12: Software | D12: 16134
A13: Jan | B13: South | C13: Services | D13: 13731 | F13: Record your PivotTable results on sheet Ex7_Pivot.
A14: Jan | B14: East | C14: Training | D14: 13333
A15: Jan | B15: North | C15: Training | D15: 13079
A16: Jan | B16: West | C16: Software | D16: 19934
A17: Jan | B17: West | C17: Hardware | D17: 8848
A18: Jan | B18: North | C18: Software | D18: 8968
A19: Jan | B19: South | C19: Training | D19: 14383
A20: Jan | B20: South | C20: Training | D20: 17780
A21: Jan | B21: West | C21: Software | D21: 14856
A22: Feb | B22: West | C22: Training | D22: 15289
A23: Feb | B23: West | C23: Training | D23: 9739
A24: Feb | B24: West | C24: Training | D24: 11897
A25: Feb | B25: North | C25: Training | D25: 13208
... A83: Jun | B83: South | C83: Training | D83: 19527
A84: Month | B84: Region | C84: Category | D84: Amount ($)
A85: Jul | B85: South | C85: Training | D85: 25286
A86: Jul | B86: South | C86: Hardware | D86: 26233
A87: Jul | B87: East | C87: Services | D87: 16415
A88: Jul | B88: South | C88: Hardware | D88: 19816
A89: Jul | B89: North | C89: Hardware | D89: 16734
A90: Jul | B90: East | C90: Software | D90: 15087
A91: Jul | B91: West | C91: Training | D91: 11233
A92: Jul | B92: North | C92: Hardware | D92: 14474
A93: Jul | B93: North | C93: Software | D93: 24841
A94: Jul | B94: North | C94: Training | D94: 19424
A95: Jul | B95: West | C95: Hardware | D95: 14164
A96: Jul | B96: North | C96: Services | D96: 18349
... A157: Dec | B157: South | C157: Training | D157: 22240

Sheet Ex7_Pivot
A1: Ex7 – PivotTable Results & Questions
A2: Fill in the totals from YOUR PivotTable. (Solutions file shows SUMIFS check formulas – they should equal the PivotTable.)
A4: Audit skills: clean structure first (one heading row, no blank rows) · PivotTable to summarise · Slicer/Filter to switch · PivotChart to see trend.
A9: Region | B9: Sum of Amount | D9: Month | E9: Sum of Amount
A10: North | B10: =SUMIFS(Ex7_PivotRaw!$D$10:$D$157,Ex7_PivotRaw!$B$10:$B$157,A10) -> 853831 | D10: Jan | E10: =SUMIFS(Ex7_PivotRaw!$D$10:$D$157,Ex7_PivotRaw!$A$10:$A$157,D10) -> 166582
A11: South | B11: =SUMIFS(Ex7_PivotRaw!$D$10:$D$157,Ex7_PivotRaw!$B$10:$B$157,A11) -> 607252 | D11: Feb | E11: =SUMIFS(Ex7_PivotRaw!$D$10:$D$157,Ex7_PivotRaw!$A$10:$A$157,D11) -> 175066
A12: East | B12: =SUMIFS(Ex7_PivotRaw!$D$10:$D$157,Ex7_PivotRaw!$B$10:$B$157,A12) -> 614573 | D12: Mar | E12: =SUMIFS(Ex7_PivotRaw!$D$10:$D$157,Ex7_PivotRaw!$A$10:$A$157,D12) -> 203950
A13: West | B13: =SUMIFS(Ex7_PivotRaw!$D$10:$D$157,Ex7_PivotRaw!$B$10:$B$157,A13) -> 565467 | D13: Apr | E13: =SUMIFS(Ex7_PivotRaw!$D$10:$D$157,Ex7_PivotRaw!$A$10:$A$157,D13) -> 219369
A14: Grand Total | B14: =SUM(B10:B13) -> 2641123 | D14: May | E14: =SUMIFS(Ex7_PivotRaw!$D$10:$D$157,Ex7_PivotRaw!$A$10:$A$157,D14) -> 198493
D15: Jun | E15: =SUMIFS(Ex7_PivotRaw!$D$10:$D$157,Ex7_PivotRaw!$A$10:$A$157,D15) -> 194767
D16: Jul | E16: =SUMIFS(Ex7_PivotRaw!$D$10:$D$157,Ex7_PivotRaw!$A$10:$A$157,D16) -> 222056
D17: Aug | E17: =SUMIFS(Ex7_PivotRaw!$D$10:$D$157,Ex7_PivotRaw!$A$10:$A$157,D17) -> 224892
D18: Sep | E18: =SUMIFS(Ex7_PivotRaw!$D$10:$D$157,Ex7_PivotRaw!$A$10:$A$157,D18) -> 246942
D19: Oct | E19: =SUMIFS(Ex7_PivotRaw!$D$10:$D$157,Ex7_PivotRaw!$A$10:$A$157,D19) -> 238407
D20: Nov | E20: =SUMIFS(Ex7_PivotRaw!$D$10:$D$157,Ex7_PivotRaw!$A$10:$A$157,D20) -> 309741
D21: Dec | E21: =SUMIFS(Ex7_PivotRaw!$D$10:$D$157,Ex7_PivotRaw!$A$10:$A$157,D21) -> 240858
D22: Grand Total | E22: =SUM(E10:E21) -> 2641123
A24: Q1. Why must the blank rows and repeated heading be removed before inserting the PivotTable?
A25: A PivotTable needs one heading row and one continuous, consistent block of data. Blank rows can cut the source range short, and a repeated heading becomes a fake 'Month' item and text in the Amount column.
A26: Q2. Your manager says: 'I don't need the 144 rows, just one total per region.' Which feature and which layout?
A27: PivotTable: Region in Rows, Amount in Values summarised by Sum. Source data stays unchanged.
A28: Q3. The manager wants to switch between Hardware, Software, etc. during a meeting. A colleague suggests one sheet per category. Better option?
A29: One PivotTable with a Slicer (or Report Filter) on Category – click to switch; no duplicated sheets to maintain.
A30: Q4. 'I can read the 12 monthly totals but want to see the direction at a glance.' What do you add, and what does it show here?
A31: A PivotChart (line/column) based on the monthly PivotTable. Here it shows a generally rising trend through the year.
A32: Q5. Do the Region Grand Total and the Month Grand Total agree? Why is that a useful check?
A33: Yes – both equal the total of all data rows. Matching grand totals confirm no rows were lost or double-counted when restructuring.

Sheet Ex8_Scenarios
A1: Ex8 – Scenario Questions (audit style)
A2: Read each situation and choose the BEST action from the dropdown in column G. In column H, write one line on why.
A4: All 20 situations mirror audit topics, but with different numbers and cell addresses. Pick the BEST action – think about what the requirement really asks.
A9: # | B9: Scenario | C9: A | D9: B | E9: C | F9: D | G9: Your answer | H9: Why? (Solutions: explanation)
A10: 1 | B10: Cells E12:E17 hold 16, 23, blank, 0, 37, blank. Your manager asks how many cells contain numbers. | C10: =COUNT(E12:E17) → 3 | D10: =COUNT(E12:E17) → 4 | E10: =COUNTBLANK(E12:E17) → 2 | F10: Count manually → 6 | G10: B | H10: COUNT includes the 0 as a number: 16, 23, 0, 37 = 4.
A11: 2 | B11: F11:F14 hold 92, blank, 74, 83. A colleague averages by dividing the total by 4. | C11: Result 62.25 is correct | D11: =AVERAGE(F11:F14) → 83 | E11: Replace blank with 0 first | F11: =SUM(F11:F14)/3 is the only way | G11: B | H11: AVERAGE ignores blanks: 249 ÷ 3 = 83.
A12: 3 | B12: Budget $2,400; actual spend $2,760. What is the % variance? | C12: 360% | D12: 15% over budget | E12: 13% over budget | F12: -15% | G12: B | H12: (2760−2400)/2400 = 15% above budget.
A13: 4 | B13: You need to apply a fixed tax rate in M3 to 500 rows by copying one formula down. | C13: =A5*M3 | D13: =A5*M$3 or =A5*$M$3 | E13: =$A$5*$M$3 | F13: Type the rate in each row | G13: B | H13: Lock the rate row; keep A5 relative so each row uses its own value.
A14: 5 | B14: A formula =F23*1.1 is copied from row 23 to row 24 and becomes =F24*1.1. | C14: Excel error – undo | D14: Correct – relative reference | E14: Must change to $F$23 | F14: Turn off auto-calc | G14: B | H14: Relative references adjust to the matching row – intended.
A15: 6 | B15: You must view only 'Returned' orders for 10 minutes; other rows must remain for later. | C15: Delete other rows | D15: Sort by Status | E15: Filter Status = Returned | F15: Copy to new file | G15: C | H15: Filter hides temporarily without changing data.
A16: 7 | B16: A list of 940 claims must show the largest claims first, with all claims still visible. | C16: Filter top 10 | D16: Sort Largest → Smallest | E16: Freeze Panes | F16: Conditional delete | G16: B | H16: Sort reorders without hiding anything.
A17: 8 | B17: On row 1,500 you can't tell which column is 'Due Date'. Data is correct. | C17: Copy headings every 65 rows | D17: Freeze Top Row | E17: Sort by heading | F17: Remove blanks | G17: B | H17: Freeze Panes is a view change only.
A18: 9 | B18: A cell holds 0.065 and must display 6.5% without changing the value. | C18: Retype it as 6.5 | D18: Type 6.5% in a new cell | E18: Apply Percentage format (1 dp) | F18: Use TEXT and delete original | G18: C | H18: Formatting changes display; stored value stays 0.065.
A19: 10 | B19: A lookup works for 49 IDs but gives #N/A for one ID. | C19: Wrap in IFERROR(…,0) immediately | D19: Check whether the ID exists / is typed differently | E19: Delete the row | F19: Rewrite the formula | G19: B | H19: #N/A = no match found; investigate before hiding.
A20: 11 | B20: =K9+L9 gives #VALUE!; K9 = 480, L9 = 'Awaited'. | C20: The + operator is wrong | D20: L9 contains text, not a number | E20: Excel needs recalculating | F20: Use SUM to hide it | G20: B | H20: Text cannot be added; fix the data, not the operator.
A21: 12 | B21: Names look like ' sARAH miller ' and some contain hidden line breaks. | C21: TRIM only | D21: PROPER only | E21: TRIM + CLEAN + PROPER | F21: Retype manually | G21: C | H21: Each fixes a different issue: spaces, hidden characters, capitalisation.
... A29: 20 | B29: A PivotTable shows 12 monthly totals; manager wants to see the trend quickly. | C29: Add a PivotChart | D29: Add more decimals | E29: Freeze Panes | F29: Text to Columns | G29: A | H29: A chart makes rise/fall patterns visible at a glance.
B31: Answer key is shown in column G (green).
